query_understanding/__init__.py
query_understanding/annotate.py
query_understanding/color.py
query_understanding/gender.py
query_understanding/price.py
query_understanding/shop.py
query_understanding/size.py
query_understanding/spell_checker.py
query_understanding/term.py
query_understanding-1.0.2.data/data/query_understanding/dataset/colors.csv
query_understanding-1.0.2.data/data/query_understanding/dataset/map_words.json
query_understanding-1.0.2.data/data/query_understanding/dataset/nltk_words.csv
query_understanding-1.0.2.data/data/query_understanding/dataset/price.csv
query_understanding-1.0.2.data/data/query_understanding/dataset/shop_name.csv
query_understanding-1.0.2.data/data/query_understanding/dataset/words.csv
query_understanding-1.0.2.dist-info/DESCRIPTION.rst
query_understanding-1.0.2.dist-info/METADATA
query_understanding-1.0.2.dist-info/RECORD
query_understanding-1.0.2.dist-info/WHEEL
query_understanding-1.0.2.dist-info/metadata.json
query_understanding-1.0.2.dist-info/top_level.txt
